lctest/__init__.py
lctest/arguments.py
lctest/lib.py
lctest/stdlib.py
lctest/test.py
lctest/testcase.py
lctest/text_format.py
lctest-0.1.8.dist-info/METADATA
lctest-0.1.8.dist-info/WHEEL
lctest-0.1.8.dist-info/top_level.txt
lctest-0.1.8.dist-info/RECORD
