Metadata-Version: 2.1
Name: lctest
Version: 0.1.8
Summary: Simulate leetcode runner
Home-page: https://lctest.readthedocs.io/
Author: Tuan Chau
Author-email: tuanchaujp@gmail.com
License: MIT
Classifier: Intended Audience :: Developers
Classifier: License :: OSI Approved :: MIT License
Classifier: Programming Language :: Python
Classifier: Programming Language :: Python :: 3
Classifier: Programming Language :: Python :: 3.6
Classifier: Programming Language :: Python :: 3.7
Classifier: Programming Language :: Python :: 3.8
Classifier: Programming Language :: Python :: 3.9
Classifier: Operating System :: OS Independent
